url_image_module/__init__.py
url_image_module/_version.py
url_image_module/classes.py
url_image_module/constants.py
url_image_module/create_image_split_folders.py
url_image_module/data_labeling_utils.py
url_image_module/make_image_labeling_csv.py
url_image_module/metric_utils.py
url_image_module/misc_utils.py
url_image_module/model_utils.py
url_image_module/os_utils.py
url_image_module/pd_utils.py
url_image_module/plotting_utils.py
url_image_module/prediction.py
url_image_module/pt_utils.py
url_image_module/testing.py
url_image_module/training.py
url_image_module-0.27.0.dist-info/LICENSE
url_image_module-0.27.0.dist-info/METADATA
url_image_module-0.27.0.dist-info/WHEEL
url_image_module-0.27.0.dist-info/top_level.txt
url_image_module-0.27.0.dist-info/RECORD
