Metadata-Version: 2.1
Name: url-image-module
Version: 0.27.0
Summary: Image Module of REACT
Home-page: https://gitlab.com/react76/url-image-module
Author: Urban Risk Lab
Author-email: url_googleai@mit.edu
License: UNKNOWN
Project-URL: Bug Tracker, https://gitlab.com/react76/url-image-module/-/issues
Platform: UNKNOWN
Classifier: Programming Language :: Python :: 3
Classifier: License :: OSI Approved :: Apache Software License
Classifier: Operating System :: OS Independent
Requires-Python: >=3.6
License-File: LICENSE
Requires-Dist: bleach (==4.1.0)
Requires-Dist: certifi (==2022.5.18.1)
Requires-Dist: charset-normalizer (==2.0.12)
Requires-Dist: colorama (==0.4.4)
Requires-Dist: cycler (==0.11.0)
Requires-Dist: dataclasses (==0.6)
Requires-Dist: docutils (==0.18.1)
Requires-Dist: efficientnet-pytorch (==0.7.1)
Requires-Dist: idna (==3.3)
Requires-Dist: importlib-metadata (==4.8.3)
Requires-Dist: importlib-resources (==5.4.0)
Requires-Dist: joblib (==1.1.0)
Requires-Dist: keyring (==23.4.1)
Requires-Dist: kiwisolver (==1.3.1)
Requires-Dist: matplotlib (==3.3.4)
Requires-Dist: numpy (==1.19.5)
Requires-Dist: packaging (==21.3)
Requires-Dist: pandas (==1.1.5)
Requires-Dist: patsy (==0.5.2)
Requires-Dist: Pillow (==8.4.0)
Requires-Dist: pkginfo (==1.8.3)
Requires-Dist: Pygments (==2.12.0)
Requires-Dist: pyparsing (==3.0.7)
Requires-Dist: python-dateutil (==2.8.2)
Requires-Dist: pytz (==2022.1)
Requires-Dist: readme-renderer (==34.0)
Requires-Dist: requests (==2.27.1)
Requires-Dist: requests-toolbelt (==0.9.1)
Requires-Dist: rfc3986 (==1.5.0)
Requires-Dist: scikit-learn (==0.24.2)
Requires-Dist: scipy (==1.5.4)
Requires-Dist: seaborn (==0.11.2)
Requires-Dist: six (==1.16.0)
Requires-Dist: statsmodels (==0.12.2)
Requires-Dist: threadpoolctl (==3.1.0)
Requires-Dist: torch (==1.9.0)
Requires-Dist: torchvision (==0.10.0)
Requires-Dist: tqdm (==4.64.0)
Requires-Dist: twine (==3.8.0)
Requires-Dist: typing-extensions (==4.1.1)
Requires-Dist: urllib3 (==1.26.9)
Requires-Dist: webencodings (==0.5.1)
Requires-Dist: zipp (==3.6.0)
